ratelimitpy
