Metadata-Version: 1.2
Name: ratelimitpy
Version: 1.1.0
Summary: Simple rate limit decorator
Home-page: https://github.com/saporitigianni/ratelimitpy
Author: Gianni Saporiti
Author-email: saporitigianni@outlook.com
License: BSD
Download-URL: https://pypi.python.org/pypi/ratelimitpy
Keywords: ratelimit,api
Platform: UNKNOWN
Classifier: Development Status :: 5 - Production/Stable
Classifier: Intended Audience :: Developers
Classifier: License :: OSI Approved :: BSD License
Classifier: Operating System :: OS Independent
Classifier: Programming Language :: Python :: 3
Classifier: Topic :: Software Development :: Build Tools
Classifier: Topic :: Internet
Requires-Python: >=3
